jupyterlab_drawio_render_extension/__init__.py
jupyterlab_drawio_render_extension/_version.py
jupyterlab_drawio_render_extension/routes.py
jupyterlab_drawio_render_extension/static/shapes.min.js
jupyterlab_drawio_render_extension/static/stencils.min.js
jupyterlab_drawio_render_extension/static/viewer-static.min.js
jupyterlab_drawio_render_extension/tests/__init__.py
jupyterlab_drawio_render_extension/tests/test_routes.py
jupyterlab_drawio_render_extension-1.0.15.data/data/etc/jupyter/jupyter_server_config.d/jupyterlab_drawio_render_extension.json
jupyterlab_drawio_render_extension-1.0.15.data/data/share/jupyter/labextensions/jupyterlab_drawio_render_extension/package.json
jupyterlab_drawio_render_extension-1.0.15.data/data/share/jupyter/labextensions/jupyterlab_drawio_render_extension/schemas/jupyterlab_drawio_render_extension/package.json.orig
jupyterlab_drawio_render_extension-1.0.15.data/data/share/jupyter/labextensions/jupyterlab_drawio_render_extension/schemas/jupyterlab_drawio_render_extension/plugin.json
jupyterlab_drawio_render_extension-1.0.15.data/data/share/jupyter/labextensions/jupyterlab_drawio_render_extension/static/420.e4390ef1359cc09e060a.js
jupyterlab_drawio_render_extension-1.0.15.data/data/share/jupyter/labextensions/jupyterlab_drawio_render_extension/static/728.435d481fc56038304251.js
jupyterlab_drawio_render_extension-1.0.15.data/data/share/jupyter/labextensions/jupyterlab_drawio_render_extension/static/remoteEntry.1076c6a6f8ca2309032e.js
jupyterlab_drawio_render_extension-1.0.15.data/data/share/jupyter/labextensions/jupyterlab_drawio_render_extension/static/style.js
jupyterlab_drawio_render_extension-1.0.15.data/data/share/jupyter/labextensions/jupyterlab_drawio_render_extension/static/third-party-licenses.json
jupyterlab_drawio_render_extension-1.0.15.data/data/share/jupyter/labextensions/jupyterlab_drawio_render_extension/install.json
jupyterlab_drawio_render_extension-1.0.15.dist-info/METADATA
jupyterlab_drawio_render_extension-1.0.15.dist-info/WHEEL
jupyterlab_drawio_render_extension-1.0.15.dist-info/licenses/LICENSE
jupyterlab_drawio_render_extension-1.0.15.dist-info/RECORD
